kavitapy/__init__.py
kavitapy/kavita.py
kavitapy/py.typed
kavitapy-0.3.0a1.dist-info/METADATA
kavitapy-0.3.0a1.dist-info/WHEEL
kavitapy-0.3.0a1.dist-info/licenses/LICENSE
kavitapy-0.3.0a1.dist-info/RECORD
