Metadata-Version: 2.1
Name: kavitapy
Version: 0.3.0a1
Summary: A python wrapper for the Kavita API
Project-URL: Homepage, https://gitlab.com/RealStickman/kavitapy
Project-URL: Bug Tracker, https://gitlab.com/RealStickman/kavitapy/issues
Author-email: RealStickman <mrc@frm01.net>
License-Expression: GPL-3.0-or-later
License-File: LICENSE
Classifier: Development Status :: 3 - Alpha
Classifier: License :: OSI Approved :: GNU General Public License v3 or later (GPLv3+)
Classifier: Operating System :: OS Independent
Classifier: Programming Language :: Python :: 3
Classifier: Programming Language :: Python :: 3.10
Requires-Python: >=3.10
Requires-Dist: requests>=2.27.0
Provides-Extra: dev
Requires-Dist: black>=23.1.0; extra == 'dev'
Requires-Dist: hatch>=1.5.0; extra == 'dev'
Requires-Dist: hatchling>=1.13.0; extra == 'dev'
Requires-Dist: pyright>=1.1.295; extra == 'dev'
Requires-Dist: virtualenv>=20.19.0; extra == 'dev'
